setup.py
src/sparrow/__init__.py
src/sparrow/allegro_backend.py
src/sparrow/base_backend.py
src/sparrow/core.py
src/sparrow/error.py
src/sparrow/interfaces.py
src/sparrow/ntriples.py
src/sparrow/rdflib_backend.py
src/sparrow/redland_backend.py
src/sparrow/sesame_backend.py
src/sparrow/utils.py
src/sparrow.egg-info/PKG-INFO
src/sparrow.egg-info/SOURCES.txt
src/sparrow.egg-info/dependency_links.txt
src/sparrow.egg-info/entry_points.txt
src/sparrow.egg-info/not-zip-safe
src/sparrow.egg-info/requires.txt
src/sparrow.egg-info/top_level.txt
src/sparrow/tests/__init__.py
src/sparrow/tests/base_tests.py
src/sparrow/tests/test_allegro.py
src/sparrow/tests/test_dict_format.py
src/sparrow/tests/test_docs.py
src/sparrow/tests/test_rdflib.py
src/sparrow/tests/test_redland.py
src/sparrow/tests/test_sesame.py