Metadata-Version: 1.0
Name: sparrow
Version: 1.0b3
Summary: Sparrow, Common RDF/SPARQL Database API
Home-page: UNKNOWN
Author: Jasper Op de Coul (Infrae)
Author-email: jasper@infrae.com
License: BSD
Keywords: python RDF SPARQL
Platform: UNKNOWN
Classifier: Development Status :: 4 - Beta
Classifier: Programming Language :: Python
Classifier: License :: OSI Approved :: BSD License
Classifier: Topic :: Software Development :: Libraries :: Python Modules
Classifier: Environment :: Web Environment
